wagtail_multi_image_edit/__init__.py
wagtail_multi_image_edit/forms.py
wagtail_multi_image_edit/views.py
wagtail_multi_image_edit/wagtail_hooks.py
wagtail_multi_image_edit/static/wagtail_multi_image_edit/admin/css/wagtail_multi_image_edit.css
wagtail_multi_image_edit/static/wagtail_multi_image_edit/admin/js/wagtail_multi_image_edit.js
wagtail_multi_image_edit/templates/wagtail_multi_image_edit/_multi_edit_form.html
wagtail_multi_image_edit/templates/wagtail_multi_image_edit/multi_edit.html
wagtail_multi_image_edit/templates/wagtailimages/images/results.html
wagtail_multi_image_edit/tests/__init__.py
wagtail_multi_image_edit/tests/settings.py
wagtail_multi_image_edit/tests/tests.py
wagtail_multi_image_edit/tests/urls.py
Wagtail_Multi_Image_Edit-0.0.5.dist-info/LICENSE
Wagtail_Multi_Image_Edit-0.0.5.dist-info/METADATA
Wagtail_Multi_Image_Edit-0.0.5.dist-info/WHEEL
Wagtail_Multi_Image_Edit-0.0.5.dist-info/top_level.txt
Wagtail_Multi_Image_Edit-0.0.5.dist-info/RECORD
