Metadata-Version: 2.1
Name: Wagtail-Multi-Image-Edit
Version: 0.0.5
Summary: Wagtail Multi Image Edit
Home-page: https://github.com/kevinhowbrook/wagtail-multi-image-edit
Author: Kevin Howbrook
Author-email: kbhowbrook@gmail.com
License: MIT License
Platform: UNKNOWN
Requires-Dist: wagtail
